README.md
setup.py
BayesSets.egg-info/PKG-INFO
BayesSets.egg-info/SOURCES.txt
BayesSets.egg-info/dependency_links.txt
BayesSets.egg-info/requires.txt
BayesSets.egg-info/top_level.txt
bayessets/__init__.py
bayessets/bayessets.py