Metadata-Version: 1.0
Name: BayesSets
Version: 0.2.1
Summary: Implementation of the Bayesian Sets algorithm and variants
Home-page: https://github.com/MaLL-UFSCar/bayessets
Author: Diorge Brognara
Author-email: diorge.bs@gmail.com
License: MIT
Keywords: bayes set expansion machine learning information retrieval
Platform: UNKNOWN
